Compiled from "LoopMap.scala"
public final class LoopMap$ {
  public static LoopMap$ MODULE$;

  public static {};
    Code:
       0: new           #2                  // class LoopMap$
       3: invokespecial #17                 // Method "<init>":()V
       6: return

  public void main(java.lang.String[]);
    Code:
       0: getstatic     #25                 // Field scala/runtime/RichInt$.MODULE$:Lscala/runtime/RichInt$;
       3: getstatic     #30                 // Field scala/Predef$.MODULE$:Lscala/Predef$;
       6: iconst_0
       7: invokevirtual #34                 // Method scala/Predef$.intWrapper:(I)I
      10: bipush        10
      12: invokevirtual #38                 // Method scala/runtime/RichInt$.until$extension0:(II)Lscala/collection/immutable/Range;
      15: invokedynamic #59,  0             // InvokeDynamic #0:apply:()Lscala/Function1;
      20: invokevirtual #65                 // Method scala/collection/immutable/Range.foreach$mVc$sp:(Lscala/Function1;)V
      23: return

  public static final void $anonfun$main$1(java.lang.Object);
    Code:
       0: getstatic     #30                 // Field scala/Predef$.MODULE$:Lscala/Predef$;
       3: aload_0
       4: invokevirtual #73                 // Method scala/Predef$.println:(Ljava/lang/Object;)V
       7: return

  private LoopMap$();
    Code:
       0: aload_0
       1: invokespecial #75                 // Method java/lang/Object."<init>":()V
       4: aload_0
       5: putstatic     #77                 // Field MODULE$:LLoopMap$;
       8: return

  public static final java.lang.Object $anonfun$main$1$adapted(java.lang.Object);
    Code:
       0: aload_0
       1: invokestatic  #79                 // Method $anonfun$main$1:(Ljava/lang/Object;)V
       4: getstatic     #85                 // Field scala/runtime/BoxedUnit.UNIT:Lscala/runtime/BoxedUnit;
       7: areturn

  private static java.lang.Object $deserializeLambda$(java.lang.invoke.SerializedLambda);
    Code:
       0: aload_0
       1: invokedynamic #97,  0             // InvokeDynamic #1:lambdaDeserialize:(Ljava/lang/invoke/SerializedLambda;)Ljava/lang/Object;
       6: areturn
}
