Compiled from "LoopMap.scala"
public final class LoopMap$ {
  public static final LoopMap$ MODULE$;

  public static {};
    Code:
       0: new           #2                  // class LoopMap$
       3: invokespecial #12                 // Method "<init>":()V
       6: return

  public LoopMap$();
    Code:
       0: aload_0
       1: invokespecial #13                 // Method java/lang/Object."<init>":()V
       4: aload_0
       5: putstatic     #15                 // Field MODULE$:LLoopMap$;
       8: return

  public void main(java.lang.String[]);
    Code:
       0: getstatic     #23                 // Field scala/runtime/RichInt$.MODULE$:Lscala/runtime/RichInt$;
       3: getstatic     #28                 // Field scala/Predef$.MODULE$:Lscala/Predef$;
       6: iconst_0
       7: invokevirtual #34                 // Method scala/LowPriorityImplicits.intWrapper:(I)I
      10: bipush        10
      12: invokevirtual #38                 // Method scala/runtime/RichInt$.until$extension0:(II)Lscala/collection/immutable/Range;
      15: aload_0
      16: invokedynamic #55,  0             // InvokeDynamic #0:applyVoid:(LLoopMap$;)Lscala/compat/java8/JProcedure1;
      21: invokevirtual #61                 // Method scala/collection/immutable/Range.foreach:(Lscala/Function1;)V
      24: return

  private void main$$anonfun$1(java.lang.Object);
    Code:
       0: getstatic     #28                 // Field scala/Predef$.MODULE$:Lscala/Predef$;
       3: aload_1
       4: invokevirtual #66                 // Method scala/Predef$.println:(Ljava/lang/Object;)V
       7: return
}
